{
    "$schema": "https://mintlify.com/docs.json",
    "theme": "maple",
    "name": "Exam Insights",
    "colors": {
        "primary": "#0FA01B",
        "light": "#0FA01B",
        "dark": "#0FA01B"
    },
    "favicon": "logo/logo.png",
    "navigation": {
        "dropdowns": [
            {
                "dropdown": "Home",
                "icon": "home",
                "pages": [
                    "home"
                ]
            },
            {
                "dropdown": "Getting Started",
                "icon": "book-open",
                "pages": [
                    "getting_started"
                ]
            },
            {
                "dropdown": "Pricing & Billing",
                "icon": "square-terminal",
                "pages": [
                    "pricing"
                ]
            },
            {
                "dropdown": "Troubleshooting",
                "icon": "square-terminal",
                "pages": [
                    "troubleshooting"
                ]
            },
            {
                "dropdown": "Contact",
                "href": "https://exam-insights.com/company/"
            }
        ]
    },
    "logo": {
        "light": "logo/logo.png",
        "dark": "logo/logo.png"
    },
    "appearance": {
        "default": "light",
        "strict": true
    },
    "navbar": {
        "links": [
            {
                "label": "Support",
                "href": "https://exam-insights.com/company/"
            }
        ],
        "primary": {
            "type": "button",
            "label": "Open app",
            "href": "https://exam-insights.com"
        }
    },
    "footer": {
        "socials": {}
    }
}